main.py
bq_to_dbt_contract-0.1.2.dist-info/METADATA
bq_to_dbt_contract-0.1.2.dist-info/WHEEL
bq_to_dbt_contract-0.1.2.dist-info/entry_points.txt
bq_to_dbt_contract-0.1.2.dist-info/top_level.txt
bq_to_dbt_contract-0.1.2.dist-info/RECORD
